README.txt
setup.py
evilupload/__init__.py
evilupload/evilupload.py
evilupload/main.py
evilupload.egg-info/PKG-INFO
evilupload.egg-info/SOURCES.txt
evilupload.egg-info/dependency_links.txt
evilupload.egg-info/entry_points.txt
evilupload.egg-info/top_level.txt